odoo10_addon_report_wkhtmltopdf_param-10.0.1.0.1-py2.7-nspkg.pth
odoo/addons/report_wkhtmltopdf_param/README.rst
odoo/addons/report_wkhtmltopdf_param/__init__.py
odoo/addons/report_wkhtmltopdf_param/__manifest__.py
odoo/addons/report_wkhtmltopdf_param/models/__init__.py
odoo/addons/report_wkhtmltopdf_param/models/report.py
odoo/addons/report_wkhtmltopdf_param/models/report_paperformat.py
odoo/addons/report_wkhtmltopdf_param/models/report_paperformat_parameter.py
odoo/addons/report_wkhtmltopdf_param/security/ir.model.access.csv
odoo/addons/report_wkhtmltopdf_param/static/description/icon.png
odoo/addons/report_wkhtmltopdf_param/tests/__init__.py
odoo/addons/report_wkhtmltopdf_param/tests/test_report_paperformat.py
odoo/addons/report_wkhtmltopdf_param/views/paperformat.xml
odoo10_addon_report_wkhtmltopdf_param-10.0.1.0.1.dist-info/DESCRIPTION.rst
odoo10_addon_report_wkhtmltopdf_param-10.0.1.0.1.dist-info/METADATA
odoo10_addon_report_wkhtmltopdf_param-10.0.1.0.1.dist-info/RECORD
odoo10_addon_report_wkhtmltopdf_param-10.0.1.0.1.dist-info/WHEEL
odoo10_addon_report_wkhtmltopdf_param-10.0.1.0.1.dist-info/metadata.json
odoo10_addon_report_wkhtmltopdf_param-10.0.1.0.1.dist-info/namespace_packages.txt
odoo10_addon_report_wkhtmltopdf_param-10.0.1.0.1.dist-info/top_level.txt
