Metadata-Version: 2.0
Name: odoo10-addon-report-wkhtmltopdf-param
Version: 10.0.1.0.1
Summary: Add new parameters for a paper format to be used by wkhtmltopdf
Home-page: https://avoin.systems
Author: Avoin.Systems,Eficent,Odoo Community Association (OCA)
Author-email: support@odoo-community.org
License: AGPL-3
Platform: UNKNOWN
Classifier: Programming Language :: Python :: 2.7
Classifier: Framework :: Odoo
Classifier: License :: OSI Approved :: GNU Affero General Public License v3
Requires-Dist: odoo (<10.1dev,>=10.0)
